mypy_protobuf/__init__.py
mypy_protobuf/extensions_pb2.py
mypy_protobuf/main.py
mypy_protobuf-4.0.0.dist-info/licenses/LICENSE
mypy_protobuf-4.0.0.dist-info/METADATA
mypy_protobuf-4.0.0.dist-info/WHEEL
mypy_protobuf-4.0.0.dist-info/entry_points.txt
mypy_protobuf-4.0.0.dist-info/top_level.txt
mypy_protobuf-4.0.0.dist-info/RECORD
