Metadata-Version: 2.4
Name: mypy-protobuf
Version: 4.0.0
Summary: Generate mypy stub files from protobuf specs
Home-page: https://github.com/nipunn1313/mypy-protobuf
Download-URL: https://github.com/nipunn1313/mypy-protobuf/releases
Author: Nipunn Koorapati
Author-email: nipunn1313@gmail.com
License: Apache License 2.0
Keywords: mypy proto dropbox
Requires-Python: >=3.8
License-File: LICENSE
Requires-Dist: protobuf>=4.25.3
Requires-Dist: types-protobuf>=4.24
Dynamic: download-url
Dynamic: license-file
